day_1/src/rtl/alu.sv
`define ADD 4'b0000
`define SUB 4'b0001
`define AND 4'b0011
`define OR 4'b0100
`define XOR 4'b0101
`define INV 4'b0110
`define SHL 4'b0111
`define SHR 4'b1000
`define LDI 4'b1001
`define MOV 4'b1010

// Module starts here

module alu (
    input  logic [3:0] alu_op,      // ALU Operations
    input  logic [7:0] operand_a,   // First operand - RS1
    input  logic [7:0] operand_b,   // Second operand - RS2 or sign ext imm
    output logic [7:0] alu_result,  // Computation result
    output logic       zero_flag,   // Zero flag 1 if result == 0
    output logic       carry_flag
);

  logic [7:0] r_result;

  assign alu_result = r_result;
  assign zero_flag  = (r_result == 8'h00) ? 1 : 0;

  always_comb begin
    r_result   = 8'h00;
    carry_flag = 1'b0;
    case (alu_op)
      `ADD: {carry_flag, r_result} = operand_a + operand_b;
      `SUB: {carry_flag, r_result} = operand_a - operand_b;
      `AND: r_result = operand_a & operand_b;
      `OR:  r_result = operand_a | operand_b;
      `XOR: r_result = operand_a ^ operand_b;
      `INV: r_result = ~operand_a;
      `SHL: r_result = operand_a << operand_b[2:0];
      `SHR: r_result = operand_a >> operand_b[2:0];
      `LDI: r_result = operand_b;
      `MOV: r_result = operand_a;
      default: begin
        r_result   = 8'h00;
        carry_flag = 1'b0;
      end
    endcase
  end


endmodule

day_1/src/rtl/register_file.sv
module register_file #(
    parameter MEM_DEPTH  = 16,
    parameter DATA_WIDTH = 8
) (
    input logic clk,
    input logic rstn,
    input logic wr_en,
    input logic [3:0] rd_addr,
    input logic [3:0] rs1_addr,
    input logic [3:0] rs2_addr,
    input logic [7:0] wr_data,
    output logic [7:0] rs1_data,
    output logic [7:0] rs2_data
);

  // Register declaration
  logic [DATA_WIDTH-1:0] reg_array[0:MEM_DEPTH-1];

  // Read logic 
  always_comb begin : RegRead
    rs1_data = (rs1_addr == 4'h0) ? 8'h00 : reg_array[rs1_addr];
    rs2_data = (rs2_addr == 4'h0) ? 8'h00 : reg_array[rs2_addr];
  end


  // Write logic
  always_ff @(posedge clk or negedge rstn) begin
    if (~rstn) begin
      for (int i = 0; i <= MEM_DEPTH - 1; i++) begin
        reg_array[i] <= {DATA_WIDTH{1'b0}};
      end
    end else begin
      if (wr_en && rd_addr != 4'b0000) begin
        reg_array[rd_addr] <= wr_data;
      end
    end
  end



endmodule

day_1/src/rtl/instruction_decoder.sv
`define ADD 4'b0000
`define SUB 4'b0001
`define ADDI 4'b0010
`define AND 4'b0011
`define OR 4'b0100
`define XOR 4'b0101
`define INV 4'b0110
`define SHL 4'b0111
`define SHR 4'b1000
`define LDI 4'b1001 
`define MOV 4'b1010 
`define CMP 4'b1011 
`define JMP 4'b1100 
`define BEQ 4'b1101 
`define BNE 4'b1110 
`define NOP 4'b1111



module instruction_decoder (
    input logic [15:0] instr,
    input logic zero_flag,
    output logic [3:0] opcode,
    output logic [3:0] rd_addr,
    output logic [3:0] rs1_addr,
    output logic [3:0] rs2_addr,
    output logic [7:0] imm,
    output logic [3:0] alu_op,
    output logic reg_wr_en,
    output logic imm_sel,
    output logic branch_en
);

  // Assignment for outputs 
  assign opcode = instr[15:12];
  assign rd_addr = instr[11:8];
  assign rs1_addr = instr[7:4];
  assign rs2_addr = instr[3:0];

  // Sign extension for 4-bit immediate (to 8-bit datapath)
  assign imm = {{4{instr[3]}}, instr[3:0]};


  always_comb begin : instruction_decoder_opcode
    // Default assignments to prevent latches and maintain clarity
    reg_wr_en = 1'b0;
    imm_sel   = 1'b0;
    branch_en = 1'b0;
    alu_op    = 4'b0000;

    case (opcode)
      `ADD: begin
        reg_wr_en = 1'b1;
        imm_sel   = 1'b0;
        alu_op    = 4'b0000;
      end
      `SUB: begin
        reg_wr_en = 1'b1;
        imm_sel   = 1'b0;
        alu_op    = 4'b0001;
      end
      `ADDI: begin
        reg_wr_en = 1'b1;
        imm_sel   = 1'b1;
        alu_op    = 4'b0000; // ALU performs ADD with imm
      end
      `AND: begin
        reg_wr_en = 1'b1;
        imm_sel   = 1'b0;
        alu_op    = 4'b0011;
      end
      `OR: begin
        reg_wr_en = 1'b1;
        imm_sel   = 1'b0;
        alu_op    = 4'b0100;
      end
      `XOR: begin
        reg_wr_en = 1'b1;
        imm_sel   = 1'b0;
        alu_op    = 4'b0101;
      end
      `INV: begin
        reg_wr_en = 1'b1;
        imm_sel   = 1'b0;
        alu_op    = 4'b0110;
      end
      `SHL: begin
        reg_wr_en = 1'b1;
        imm_sel   = 1'b1;
        alu_op    = 4'b0111;
      end
      `SHR: begin
        reg_wr_en = 1'b1;
        imm_sel   = 1'b1;
        alu_op    = 4'b1000;
      end
      `LDI: begin
        reg_wr_en = 1'b1;
        imm_sel   = 1'b1;
        alu_op    = 4'b1001; // PASS_B in ALU
      end
      `MOV: begin
        reg_wr_en = 1'b1;
        imm_sel   = 1'b0;
        alu_op    = 4'b1010; // PASS_A in ALU
      end
      `CMP: begin
        reg_wr_en = 1'b0; // No writeback
        imm_sel   = 1'b0;
        alu_op    = 4'b0001; // ALU performs SUB
      end
      `JMP: begin
        reg_wr_en = 1'b0;
        imm_sel   = 1'b1;
        branch_en = 1'b1;
        alu_op    = 4'b0000; // PC <- RS1 + IMM
      end
      `BEQ: begin
        reg_wr_en = 1'b0;
        if (zero_flag) branch_en = 1'b1;
      end
      `BNE: begin
        reg_wr_en = 1'b0;
        if (!zero_flag) branch_en = 1'b1;
      end
      `NOP: begin
        // Defaults handle NOP (no write, no branch)
      end
      default: begin
        // Default behavior matches NOP
      end
    endcase
  end

endmodule

day_1/src/rtl/instruction_mem.sv
module instruction_mem #(
    parameter MEM_DEPTH = 256
) (
    input  logic [15:0] addr,
    output logic [15:0] instr
);

  // memory declaration
  logic [15:0] mem[0:MEM_DEPTH-1];

  // initialize the memory
  initial begin
    $readmempath(".");
    $readmemh("/home/praba/Projects/NanoCore16/src/rtl/inst_mem.hex", mem);
  end

  // Read the memory data
  assign instr = mem[addr[7:0]];



endmodule

day_1/src/rtl/program_counter.sv
module program_counter (
    // Global signals
    input  logic        clk,
    input  logic        rstn,       // Active-low asynchronous reset

    // Control signals
    input  logic        pc_en,      // PC enable (hold PC when deasserted)
    input  logic        branch_en,  // Branch enable (load branch target)
    input  logic [15:0] branch_target, // Branch/jump target address

    // Output
    output logic [15:0] pc_out      // Current program counter value
);

    // Internal next-PC logic
    logic [15:0] pc_next;

    // Next PC: branch target if branching, otherwise PC + 1
    assign pc_next = branch_en ? branch_target : (pc_out + 16'h0001);

    // Sequential PC register with async active-low reset
    always_ff @(posedge clk or negedge rstn) begin
        if (~rstn)
            pc_out <= 16'h0000;
        else if (pc_en)
            pc_out <= pc_next;
    end

endmodule

day_1/src/rtl/nanocore16.sv
/* 
 * =================================================================================================
 * MODULE: NanoCore16 Single-Cycle Processor (Top-Level)
 * =================================================================================================
 * ARCHITECTURE OVERVIEW:
 * NanoCore16 is an 8-bit RISC-style CPU utilizing a 16-bit fixed-length instruction format. 
 * This top-level module serves as the primary integration point for the following sub-modules:
 * 
 * 1. pc_unit        : Manages the 16-bit Program Counter and next-address selection logic.
 * 2. instruction_mem: Stores the program code and provides combinational read access.
 * 3. decoder        : Translates instructions into control signals (opcode, reg-write, imm-sel, etc.).
 * 4. register_file  : A 16x8 GPR file with R0 hardwired to zero for architectural consistency.
 * 5. alu            : Performs all arithmetic, logical, and passing operations.
 * 
 * INSTRUCTION FORMAT (16-bit fixed):
 * +-----------+----------+----------+-----------+
 * |  OPCODE   |    Rd    |   RS1    | RS2 / IMM |
 * +-----------+----------+----------+-----------+
 *    [15:12]    [11:8]     [7:4]      [3:0]
 * 
 * SUPPORTED ISA:
 * - Arithmetic: ADD, SUB, ADDI
 * - Logic     : AND, OR, XOR, INV
 * - Shift     : SHL, SHR
 * - Data      : LDI, MOV
 * - Branch/Jump: JMP, BEQ, BNE, NOP
 * - Compare   : CMP (Sets flags without writeback)
 * 
 * DESIGN PHILOSOPHY:
 * - Modularity: Each stage (Fetch, Decode, Execute, Writeback) is encapsulated.
 * - Single-Cycle: All operations complete in one clock cycle; no pipelining or hazard stalls.
 * - Hardware Zero: R0 implementation follows classic RISC patterns.
 * =================================================================================================
 */

module nanocore16 (
    // Global signals
    input logic clk,
    input logic rstn,

    // Output signals
    output logic [7:0] seg0,
    output logic [7:0] seg1,
    output logic [7:0] seg2,
    output logic [7:0] seg3
);

  /* 
   * STEP 1: Internal Signal Declarations
   * Define intermediate logic for all module interconnections (pc_out, instr, signals).
   */
  logic [15:0] pc_out;  // Connects PC to Memory
  logic [15:0] instr;  // Holds the fetched instruction
  logic [15:0] branch_target;  // Next address on branch/jump
  logic        branch_en;  // Control signal for branch/jump
  logic [15:0] relative_target;

  // decoder outputs
  logic [3:0] opcode, rd_addr, rs1_addr, rs2_addr, alu_op;
  logic [7:0] imm;
  logic reg_wr_en, imm_sel;

  // Register file outputs
  logic [7:0] rs1_data, rs2_data;

  // Feedback/ALU results
  logic [7:0] alu_result;
  logic zero_flag, carry_flag;
  logic [7:0] operand_b;




  /* 
   * STEP 2: Instruction Fetch (IF) Logic
   * Instantiate 'program_counter' and 'instruction_mem'.
   * PC target selection for JMP/Branch happens here.
   */

  // Program counter
  program_counter u_pc (
      .clk          (clk),
      .rstn         (rstn),
      .pc_en        (1'b1),           // PC always set to 1 .
      .branch_en    (branch_en),
      .branch_target(branch_target),
      .pc_out       (pc_out)
  );


  // Instruction Memory
  instruction_mem u_ins_mem (
      .addr (pc_out),
      .instr(instr)
  );

  /* 
   * STEP 3: Instruction Decode (ID) Logic
   * Instantiate 'instruction_decoder' and 'register_file'.
   * Decouple field extraction from control signal logic.
   */

  // Instruction decoder  
  instruction_decoder u_inst_decoder (
      .instr(instr),
      .zero_flag(zero_flag),
      .opcode(opcode),
      .rd_addr(rd_addr),
      .rs1_addr(rs1_addr),
      .rs2_addr(rs2_addr),
      .imm(imm),
      .alu_op(alu_op),
      .reg_wr_en(reg_wr_en),
      .imm_sel(imm_sel),
      .branch_en(branch_en)
  );

  // Register file instantiation
  register_file u_reg_file (
      .clk(clk),
      .rstn(rstn),
      .wr_en(reg_wr_en),
      .rd_addr(rd_addr),
      .rs1_addr(rs1_addr),
      .rs2_addr(rs2_addr),
      .wr_data(alu_result),
      .rs1_data(rs1_data),
      .rs2_data(rs2_data)
  );
  /* 
   * STEP 4: Execution (EX) Logic
   * Instantiate 'alu'.
   * Implement Operand B mux (Register vs. Immediate).
   */

  // ALU integration.
  // operand_b MUX implementaiton, it selects between the operand_b from rs2_data or imm value
  assign operand_b = (imm_sel) ? imm : rs2_data;

  // ALU
  alu u_alu (
      .alu_op(alu_op),
      .operand_a(rs1_data),
      .operand_b(operand_b),
      .alu_result(alu_result),
      .zero_flag(zero_flag),
      .carry_flag(carry_flag)
  );


  /* 
   * STEP 5: Control flow and Writeback
   * Resolve branch/jump targets and connect ALU result to Register File write port.
   */
  assign relative_target = (pc_out + 16'h0001) + {{12{instr[3]}}, instr[3:0]};
  assign branch_target   = (opcode == 4'b1100) ? {8'h00, alu_result} : relative_target;
endmodule

day_1/verif/testbench/nanocore16_tb.sv
`timescale 1ns / 1ps

module nanocore16_tb;

  // Signals
  logic clk;
  logic rstn;
  logic [7:0] seg0, seg1, seg2, seg3;

  // Instantiate Top-Level Processor
  nanocore16 dut (
      .clk (clk),
      .rstn(rstn),
      .seg0(seg0),
      .seg1(seg1),
      .seg2(seg2),
      .seg3(seg3)
  );

  // Clock generation
  initial begin
    clk = 0;
    forever #5 clk = ~clk;  // 100MHz clock
  end

  // Test Procedure
  initial begin
    $display("--------------------------------------------------");
    $display("Starting NanoCore-16 Processor Simulation...");
    $display("--------------------------------------------------");

    // Setup Waveform dump
    $dumpfile("processor_sim.vcd");
    $dumpvars(0, nanocore16_tb);

    // Reset
    rstn = 0;
    #20;
    rstn = 1;

    // Monitor Register Writes
    $display("Time  | PC   | Instruction | Rd | Result | Zero");
    $display("--------------------------------------------------");

    // Run for 100 cycles or until end of program
    begin : test_loop
      bit done = 0;
      for (int i = 0; i < 8 && !done; i++) begin
        @(posedge clk);
 //       #1;  // Wait for logic to settle
        $display("%4t | %h | %h        | R%0d | %h     | %b", $time, dut.pc_out, dut.instr,
                 dut.rd_addr, dut.alu_result, dut.zero_flag);

        // Check for NOP at high memory or specific exit condition
        if (dut.instr == 16'hF000 && dut.pc_out > 16'h0010) begin
          $display("--------------------------------------------------");
          $display("Program termination detected (NOP).");
          done = 1;
        end
      end
    end

    $display("--------------------------------------------------");
    $display("Simulation Final Register State:");
    for (int j = 0; j < 16; j++) begin
      $display("R%0d: %h", j, dut.u_reg_file.reg_array[j]);
    end
    $display("--------------------------------------------------");

    $finish;
  end

endmodule

day_1/verif/iverilog/processor_sim.vcd
$date
	Mon Apr  6 17:11:03 2026
$end
$version
	Icarus Verilog
$end
$timescale
	1ps
$end
$scope module nanocore16_tb $end
$var wire 8 ! seg3 [7:0] $end
$var wire 8 " seg2 [7:0] $end
$var wire 8 # seg1 [7:0] $end
$var wire 8 $ seg0 [7:0] $end
$var reg 1 % clk $end
$var reg 1 & rstn $end
$scope module dut $end
$var wire 1 % clk $end
$var wire 1 & rstn $end
$var wire 1 ' zero_flag $end
$var wire 8 ( rs2_data [7:0] $end
$var wire 4 ) rs2_addr [3:0] $end
$var wire 8 * rs1_data [7:0] $end
$var wire 4 + rs1_addr [3:0] $end
$var wire 16 , relative_target [15:0] $end
$var wire 1 - reg_wr_en $end
$var wire 4 . rd_addr [3:0] $end
$var wire 16 / pc_out [15:0] $end
$var wire 8 0 operand_b [7:0] $end
$var wire 4 1 opcode [3:0] $end
$var wire 16 2 instr [15:0] $end
$var wire 1 3 imm_sel $end
$var wire 8 4 imm [7:0] $end
$var wire 1 5 carry_flag $end
$var wire 16 6 branch_target [15:0] $end
$var wire 1 7 branch_en $end
$var wire 8 8 alu_result [7:0] $end
$var wire 4 9 alu_op [3:0] $end
$var reg 8 : seg0 [7:0] $end
$var reg 8 ; seg1 [7:0] $end
$var reg 8 < seg2 [7:0] $end
$var reg 8 = seg3 [7:0] $end
$scope module u_alu $end
$var wire 8 > alu_result [7:0] $end
$var wire 8 ? operand_b [7:0] $end
$var wire 1 ' zero_flag $end
$var wire 8 @ operand_a [7:0] $end
$var wire 4 A alu_op [3:0] $end
$var reg 1 5 carry_flag $end
$var reg 8 B r_result [7:0] $end
$upscope $end
$scope module u_ins_mem $end
$var wire 16 C instr [15:0] $end
$var wire 16 D addr [15:0] $end
$upscope $end
$scope module u_inst_decoder $end
$var wire 16 E instr [15:0] $end
$var wire 1 ' zero_flag $end
$var wire 4 F rs2_addr [3:0] $end
$var wire 4 G rs1_addr [3:0] $end
$var wire 4 H rd_addr [3:0] $end
$var wire 4 I opcode [3:0] $end
$var wire 8 J imm [7:0] $end
$var reg 4 K alu_op [3:0] $end
$var reg 1 7 branch_en $end
$var reg 1 3 imm_sel $end
$var reg 1 - reg_wr_en $end
$scope begin instruction_decoder_opcode $end
$upscope $end
$upscope $end
$scope module u_pc $end
$var wire 1 7 branch_en $end
$var wire 16 L branch_target [15:0] $end
$var wire 1 % clk $end
$var wire 1 M pc_en $end
$var wire 1 & rstn $end
$var wire 16 N pc_next [15:0] $end
$var reg 16 O pc_out [15:0] $end
$upscope $end
$scope module u_reg_file $end
$var wire 1 % clk $end
$var wire 4 P rd_addr [3:0] $end
$var wire 4 Q rs1_addr [3:0] $end
$var wire 4 R rs2_addr [3:0] $end
$var wire 1 & rstn $end
$var wire 8 S wr_data [7:0] $end
$var wire 1 - wr_en $end
$var reg 8 T rs1_data [7:0] $end
$var reg 8 U rs2_data [7:0] $end
$scope begin $ivl_for_loop0 $end
$var integer 32 V i [31:0] $end
$upscope $end
$scope begin RegRead $end
$upscope $end
$upscope $end
$upscope $end
$scope begin $ivl_for_loop2 $end
$var integer 32 W j [31:0] $end
$upscope $end
$scope begin test_loop $end
$var reg 1 X done $end
$scope begin $ivl_for_loop1 $end
$var integer 32 Y i [31:0] $end
$upscope $end
$upscope $end
$upscope $end
$enddefinitions $end
#0
$dumpvars
b0 Y
0X
b0 W
b10000 V
b0 U
b0 T
b10 S
b10 R
b0 Q
b1 P
b0 O
b1 N
1M
b11 L
b1001 K
b10 J
b1001 I
b1 H
b0 G
b10 F
b1001000100000010 E
b0 D
b1001000100000010 C
b10 B
b1001 A
b0 @
b10 ?
b10 >
bx =
bx <
bx ;
bx :
b1001 9
b10 8
07
b11 6
05
b10 4
13
b1001000100000010 2
b1001 1
b10 0
b0 /
b1 .
1-
b11 ,
b0 +
b0 *
b10 )
b0 (
0'
0&
0%
bx $
bx #
bx "
bx !
$end
#5000
b10000 V
1%
#10000
0%
#15000
b10000 V
1%
#20000
0%
1&
#25000
b11 0
b11 ?
b10 .
b10 H
b10 P
b11 )
b11 F
b11 R
b11 4
b11 J
b11 8
b11 >
b11 S
b11 B
b10 N
b1001001000000011 2
b1001001000000011 C
b1001001000000011 E
b101 6
b101 L
b1001 9
b1001 A
b1001 K
13
1-
b101 ,
b1 /
b1 D
b1 O
b1 Y
1%
#30000
0%
#35000
b10 (
b10 U
b11 *
b11 @
b11 T
b101 8
b101 >
b101 S
b101 B
b10 0
b10 ?
b0 1
b0 I
b11 .
b11 H
b11 P
b10 +
b10 G
b10 Q
b1 )
b1 F
b1 R
b1 4
b1 J
b0 9
b0 A
b0 K
03
1-
b11 N
b1100100001 2
b1100100001 C
b1100100001 E
b100 6
b100 L
b100 ,
b10 /
b10 D
b10 O
b10 Y
1%
#40000
0%
#45000
b1 8
b1 >
b1 S
b1 B
b1 9
b1 A
b1 K
b1 1
b1 I
b100 .
b100 H
b100 P
b100 N
b1010000100001 2
b1010000100001 C
b1010000100001 E
b101 6
b101 L
1-
b101 ,
b11 /
b11 D
b11 O
b11 Y
1%
#50000
0%
#55000
1'
b0 0
b0 ?
b0 (
b0 U
b0 *
b0 @
b0 T
b0 8
b0 >
b0 S
b0 B
b1111 1
b1111 I
b0 .
b0 H
b0 P
b0 +
b0 G
b0 Q
b0 )
b0 F
b0 R
b0 4
b0 J
b0 9
b0 A
b0 K
0-
b101 N
b1111000000000000 2
b1111000000000000 C
b1111000000000000 E
b101 6
b101 L
b101 ,
b100 /
b100 D
b100 O
b100 Y
1%
#60000
0%
#65000
x'
bx 0
bx ?
x5
bx 8
bx >
bx S
bx B
bx (
bx U
bx *
bx @
bx T
bx 1
bx I
bx .
bx H
bx P
bx +
bx G
bx Q
bx )
bx F
bx R
bx 4
bx J
b110 N
bx 2
bx C
bx E
bx 6
bx L
bx ,
b101 /
b101 D
b101 O
b101 Y
1%
#70000
0%
#75000
b111 N
b110 /
b110 D
b110 O
b110 Y
1%
#80000
0%
#85000
b1000 N
b111 /
b111 D
b111 O
b111 Y
1%
#90000
0%
#95000
b1001 N
b1000 /
b1000 D
b1000 O
b10000 W
b1000 Y
1%
